dcc_utils/__init__.py
dcc_utils/dcc.py
dcc_utils/exceptions.py
dcc_utils/rule.py
dcc_utils/utils.py
dcc_utils-0.2.1.dist-info/LICENSE
dcc_utils-0.2.1.dist-info/METADATA
dcc_utils-0.2.1.dist-info/WHEEL
dcc_utils-0.2.1.dist-info/top_level.txt
dcc_utils-0.2.1.dist-info/RECORD
