Metadata-Version: 2.1
Name: dcc-utils
Version: 0.2.1
Summary: DCC utils for Python
Home-page: https://github.com/italia/dcc-utils
Author: Andrea Stagi
Author-email: stagi.andrea@gmail.com
License: MIT
Platform: UNKNOWN
Classifier: Intended Audience :: Developers
Classifier: Programming Language :: Python
Classifier: Programming Language :: Python :: 3
License-File: LICENSE
Requires-Dist: base45 (==0.4.3)
Requires-Dist: cbor2 (==5.4.1)
Requires-Dist: cose (==0.9.dev8)
Requires-Dist: panzi-json-logic (==1.0.1)
Requires-Dist: Pillow (==8.3.1)
Requires-Dist: pyzbar (==0.1.8)
Requires-Dist: typing-extensions (==3.10.0.0)
